trufflehog3/__init__.py
trufflehog3/__main__.py
trufflehog3/cli.py
trufflehog3/core.py
trufflehog3/helper.py
trufflehog3/models.py
trufflehog3/render.py
trufflehog3/search.py
trufflehog3/source.py
trufflehog3/static/report.html.j2
trufflehog3/static/report.text.j2
trufflehog3/static/rules.yml
trufflehog3-3.0.10.dist-info/LICENSE
trufflehog3-3.0.10.dist-info/METADATA
trufflehog3-3.0.10.dist-info/WHEEL
trufflehog3-3.0.10.dist-info/entry_points.txt
trufflehog3-3.0.10.dist-info/top_level.txt
trufflehog3-3.0.10.dist-info/RECORD
