Metadata-Version: 2.1
Name: trufflehog3
Version: 3.0.10
Summary: Find secrets in your codebase
Home-page: https://github.com/feeltheajf/trufflehog3
Author: Ilya Radostev
Author-email: feeltheajf@gmail.com
License: GNU
Requires-Python: >=3.7
License-File: LICENSE
Requires-Dist: attrs (==20.3.0)
Requires-Dist: GitPython (==3.1.41)
Requires-Dist: Jinja2 (==3.1.4)
Requires-Dist: PyYAML (==6.0.1)
